iblbrainviewer/__init__.py
iblbrainviewer/api.py
iblbrainviewer/mappings.py
iblbrainviewer/region_info.pqt
iblbrainviewer/region_tree.pqt
iblbrainviewer/tests/test_api.py
iblbrainviewer/tests/test_mappings.py
iblbrainviewer-1.1.1.dist-info/LICENSE
iblbrainviewer-1.1.1.dist-info/METADATA
iblbrainviewer-1.1.1.dist-info/WHEEL
iblbrainviewer-1.1.1.dist-info/top_level.txt
iblbrainviewer-1.1.1.dist-info/RECORD
