Metadata-Version: 2.1
Name: iblbrainviewer
Version: 1.1.1
Summary: IBL API for atlas website
Author-email: IBL staff <info@internationalbrainlab.org>
License: MIT License
Project-URL: Homepage, https://github.com/int-brain-lab/iblbrainviewer
Project-URL: Website, https://atlas.internationalbrainlab.org
Project-URL: Documentation, https://github.com/int-brain-lab/iblbrainviewer/tree/main/docs
Project-URL: ChangeLog, https://github.com/int-brain-lab/iblbrainviewer/blob/main/CHANGELOG.md
Project-URL: Bug Tracker, https://github.com/int-brain-lab/iblbrainviewer/issues
Classifier: Programming Language :: Python :: 3
Classifier: License :: OSI Approved :: MIT License
Classifier: Operating System :: OS Independent
Requires-Python: >=3.8
License-File: LICENSE
Requires-Dist: numpy
Requires-Dist: requests
Requires-Dist: iblatlas
Requires-Dist: iblutil
